AUTHORS.rst
CONTRIBUTING.rst
HISTORY.rst
LICENSE
MANIFEST.in
README.rst
setup.py
feincms_bounds/__init__.py
feincms_bounds/admin.py
feincms_bounds/exceptions.py
feincms_bounds/models.py
feincms_bounds.egg-info/PKG-INFO
feincms_bounds.egg-info/SOURCES.txt
feincms_bounds.egg-info/dependency_links.txt
feincms_bounds.egg-info/not-zip-safe
feincms_bounds.egg-info/requires.txt
feincms_bounds.egg-info/top_level.txt
feincms_bounds/static/feincms_bounds/img/actions_placeholder.gif