Metadata-Version: 1.1
Name: feincms-bounds
Version: 0.1.0
Summary: FeinCMS add-on which adds extra admin Page validation
Home-page: https://github.com/marcofucci/feincms-bounds
Author: Marco Fucci
Author-email: info@marcofucci.com
License: BSD
Keywords: feincms
Platform: UNKNOWN
Classifier: Development Status :: 4 - Beta
Classifier: Framework :: Django
Classifier: Intended Audience :: Developers
Classifier: License :: OSI Approved :: BSD License
Classifier: Natural Language :: English
Classifier: Programming Language :: Python :: 2
Classifier: Programming Language :: Python :: 2.6
Classifier: Programming Language :: Python :: 2.7
